agent_flight_recorder/__init__.py
agent_flight_recorder/analytics.py
agent_flight_recorder/batch_operations.py
agent_flight_recorder/cli.py
agent_flight_recorder/filtering.py
agent_flight_recorder/interceptors.py
agent_flight_recorder/logging_config.py
agent_flight_recorder/providers.py
agent_flight_recorder/recorder.py
agent_flight_recorder/storage.py
agent_flight_recorder/streaming.py
agent_flight_recorder-0.2.0.dist-info/LICENSE
agent_flight_recorder-0.2.0.dist-info/METADATA
agent_flight_recorder-0.2.0.dist-info/WHEEL
agent_flight_recorder-0.2.0.dist-info/entry_points.txt
agent_flight_recorder-0.2.0.dist-info/top_level.txt
agent_flight_recorder-0.2.0.dist-info/RECORD
