Metadata-Version: 2.1
Name: agent-flight-recorder
Version: 0.2.0
Summary: Debug AI Agents without burning money
Home-page: https://github.com/0xdivin3/agent-flight-recorder
Author: 0xdivin3
Author-email: chukwuebukawilliams6@gmail.com
Classifier: Programming Language :: Python :: 3
Classifier: Programming Language :: Python :: 3.8
Classifier: Programming Language :: Python :: 3.9
Classifier: Programming Language :: Python :: 3.10
Classifier: Programming Language :: Python :: 3.11
Classifier: Operating System :: OS Independent
Classifier: License :: OSI Approved :: MIT License
Classifier: Development Status :: 4 - Beta
Classifier: Intended Audience :: Developers
Classifier: Topic :: Software Development :: Libraries
Requires-Python: >=3.8
License-File: LICENSE
